lightning_graphcore/__about__.py
lightning_graphcore/__init__.py
lightning_graphcore/accelerator.py
lightning_graphcore/precision.py
lightning_graphcore/strategy.py
lightning_graphcore/utils.py
lightning_graphcore-0.1.0.dist-info/LICENSE
lightning_graphcore-0.1.0.dist-info/METADATA
lightning_graphcore-0.1.0.dist-info/WHEEL
lightning_graphcore-0.1.0.dist-info/top_level.txt
lightning_graphcore-0.1.0.dist-info/RECORD
