Metadata-Version: 2.1
Name: lightning-graphcore
Version: 0.1.0
Summary: Lightning support for GraphCore accelerators
Home-page: https://github.com/Lightning-AI/lightning-graphcore
Download-URL: https://github.com/Lightning-AI/lightning-graphcore
Author: Lightning-AI et al.
Author-email: name@lightning.ai
License: Apache-2.0
Project-URL: Bug Tracker, https://github.com/Lightning-AI/lightning-graphcore/issues
Project-URL: Documentation, https://lightning-graphcore.rtfd.io/en/latest/
Project-URL: Source Code, https://github.com/Lightning-AI/lightning-graphcore
Keywords: deep learning,pytorch,AI
Classifier: Environment :: Console
Classifier: Natural Language :: English
Classifier: Development Status :: 3 - Alpha
Classifier: Intended Audience :: Developers
Classifier: Topic :: Scientific/Engineering :: Artificial Intelligence
Classifier: Topic :: Scientific/Engineering :: Information Analysis
Classifier: License :: OSI Approved :: Apache Software License
Classifier: Operating System :: OS Independent
Classifier: Programming Language :: Python :: 3
Classifier: Programming Language :: Python :: 3.8
Classifier: Programming Language :: Python :: 3.9
Classifier: Programming Language :: Python :: 3.10
Classifier: Programming Language :: Python :: 3.11
Requires-Python: >=3.8
License-File: LICENSE
Requires-Dist: lightning-utilities >=0.7.0
